TVDCondat2013.cpython-39-darwin.so
docs/conf.py
tvdcondat2013-0.0.9.dist-info/RECORD
tvdcondat2013-0.0.9.dist-info/WHEEL
tvdcondat2013-0.0.9.dist-info/top_level.txt
tvdcondat2013-0.0.9.dist-info/METADATA
tvdcondat2013-0.0.9.dist-info/licenses/LICENSE
