Metadata-Version: 2.4
Name: TVDCondat2013
Version: 0.0.9
Summary: Python port of Condat (2013) 1D Total Variation Denoising using pybind11 and NumPy
Home-page: https://github.com/bgailleton/TVDCondat2013
Author: Boris Gailleton
Author-email: Boris Gailleton <b.gailleton@sms.ed.ac.uk>
License: CeCILL FREE SOFTWARE LICENSE AGREEMENT
Project-URL: Homepage, https://github.com/bgailleton/TVDCondat2013
Requires-Python: >=3.8
License-File: LICENSE
Requires-Dist: numpy
Dynamic: author
Dynamic: home-page
Dynamic: license-file
